trustpoint_core/__init__.py
trustpoint_core/archiver.py
trustpoint_core/crypto_types.py
trustpoint_core/oid.py
trustpoint_core/py.typed
trustpoint_core/serializer.py
trustpoint_core-0.2.5.dist-info/METADATA
trustpoint_core-0.2.5.dist-info/WHEEL
trustpoint_core-0.2.5.dist-info/licenses/LICENSE
trustpoint_core-0.2.5.dist-info/RECORD
