Metadata-Version: 2.4
Name: trustpoint-core
Version: 0.2.5
Summary: Trustpoint core functionalities used by several other Trustpoint repositories.
License-File: LICENSE
Requires-Python: >=3.12
Requires-Dist: cryptography>=45.0.3
Requires-Dist: hatchling>=1.27.0
